drf_spectacular_extras/__init__.py
drf_spectacular_extras/settings.py
drf_spectacular_extras/views.py
drf_spectacular_extras/templates/drf_spectacular/scalar.html
drf_spectacular_extras-0.1.0.dist-info/METADATA
drf_spectacular_extras-0.1.0.dist-info/WHEEL
drf_spectacular_extras-0.1.0.dist-info/licenses/AUTHORS.rst
drf_spectacular_extras-0.1.0.dist-info/licenses/LICENSE
drf_spectacular_extras-0.1.0.dist-info/RECORD
