Metadata-Version: 2.4
Name: drf_spectacular_extras
Version: 0.1.0
Summary: Additional extensions and utilities for drf-spectacular.
Project-URL: Documentation, https://drf-spectacular-extras.readthedocs.io/
Project-URL: Homepage, https://github.com/huynguyengl99/drf-spectacular-extras
Project-URL: Repository, https://github.com/huynguyengl99/drf-spectacular-extras
Author-email: Huy Nguyen <danghuy1999@gmail.com>
License: MIT License
License-File: AUTHORS.rst
License-File: LICENSE
Classifier: Environment :: Web Environment
Classifier: Intended Audience :: Developers
Classifier: Intended Audience :: Information Technology
Classifier: License :: OSI Approved :: BSD License
Classifier: Operating System :: OS Independent
Classifier: Programming Language :: Python :: 3
Classifier: Programming Language :: Python :: 3 :: Only
Classifier: Programming Language :: Python :: 3.10
Classifier: Programming Language :: Python :: 3.11
Classifier: Programming Language :: Python :: 3.12
Classifier: Programming Language :: Python :: 3.13
Classifier: Topic :: Internet :: WWW/HTTP
Classifier: Topic :: Internet :: WWW/HTTP :: Dynamic Content
Classifier: Topic :: Software Development
Classifier: Topic :: Software Development :: Libraries
Classifier: Topic :: Software Development :: Libraries :: Application Frameworks
Requires-Python: <4.0,>=3.10
Requires-Dist: drf-spectacular<1,>=0.28.0
